odoo8_addon_exportsage50-8.0.1.0.0-py2.7-nspkg.pth
odoo_addons/exportsage50/__openerp__.py
odoo_addons/exportsage50/__init__.py
odoo_addons/exportsage50/AUTHORS.txt
odoo_addons/exportsage50/security/ir.model.access.csv
odoo_addons/exportsage50/i18n/exportsage50.pot
odoo_addons/exportsage50/wizard/exportsage50.xml
odoo_addons/exportsage50/wizard/__init__.py
odoo_addons/exportsage50/wizard/exportsage50.py
odoo_addons/exportsage50/docs/dev-import.pdf
odoo_addons/exportsage50/docs/Guide_Export_Sage_50_OpenERP_FR.pdf
odoo_addons/exportsage50/static/src/img/icon.png
odoo8_addon_exportsage50-8.0.1.0.0.dist-info/top_level.txt
odoo8_addon_exportsage50-8.0.1.0.0.dist-info/WHEEL
odoo8_addon_exportsage50-8.0.1.0.0.dist-info/RECORD
odoo8_addon_exportsage50-8.0.1.0.0.dist-info/metadata.json
odoo8_addon_exportsage50-8.0.1.0.0.dist-info/DESCRIPTION.rst
odoo8_addon_exportsage50-8.0.1.0.0.dist-info/METADATA
odoo8_addon_exportsage50-8.0.1.0.0.dist-info/namespace_packages.txt
